excel_submission_broker/__init__.py
excel_submission_broker/clean.py
excel_submission_broker/load.py
excel_submission_broker/markup.py
excel_submission_broker/submission.py
excel_submission_broker/validate.py
excel_submission_broker-0.1.2.dist-info/LICENSE
excel_submission_broker-0.1.2.dist-info/METADATA
excel_submission_broker-0.1.2.dist-info/WHEEL
excel_submission_broker-0.1.2.dist-info/top_level.txt
excel_submission_broker-0.1.2.dist-info/RECORD
