Metadata-Version: 2.1
Name: excel-submission-broker
Version: 0.1.2
Summary: A library written in Python to handle spreadsheet submission brokering into EBI archives.
Home-page: https://github.com/ebi-ait/excel-submission-broker
License: UNKNOWN
Platform: UNKNOWN
Classifier: Development Status :: 3 - Alpha
Classifier: Programming Language :: Python :: 3
Classifier: Operating System :: OS Independent
Requires-Dist: openpyxl
Requires-Dist: submission-broker
